{
  "accentColor": "{{appsmith.theme.colors.primaryColor}}",
  "animateLoading": true,
  "autoFocus": false,
  "borderRadius": "0px",
  "bottomRow": 20,
  "boxShadow": "none",
  "defaultText": "{{tbl_kycList.triggeredRow.firstname}}",
  "displayName": "Input",
  "dynamicBindingPathList": [
    {
      "key": "accentColor"
    },
    {
      "key": "defaultText"
    }
  ],
  "dynamicHeight": "FIXED",
  "dynamicTriggerPathList": [],
  "hideCard": false,
  "iconAlign": "left",
  "iconSVG": "/static/media/icon.9f505595da61a34f563dba82adeb06ec.svg",
  "inputType": "TEXT",
  "isDeprecated": false,
  "isDisabled": false,
  "isLoading": false,
  "isRequired": false,
  "isVisible": true,
  "key": "nw9xxk0e4b",
  "label": "First Name",
  "labelAlignment": "left",
  "labelPosition": "Top",
  "labelStyle": "",
  "labelTextColor": "#52525b",
  "labelTextSize": "0.875rem",
  "labelWidth": 5,
  "leftColumn": 1,
  "maxDynamicHeight": 9000,
  "minDynamicHeight": 4,
  "minWidth": 450,
  "originalBottomRow": 28,
  "originalTopRow": 22,
  "parentColumnSpace": 11.59375,
  "parentId": "w7dptrkv33",
  "parentRowSpace": 10,
  "renderMode": "CANVAS",
  "resetOnSubmit": true,
  "responsiveBehavior": "fill",
  "rightColumn": 32,
  "searchTags": [
    "form",
    "text input",
    "number",
    "textarea"
  ],
  "showStepArrows": false,
  "topRow": 13,
  "type": "INPUT_WIDGET_V2",
  "version": 2,
  "widgetId": "1n4ftir9ul",
  "widgetName": "Input1"
}